codesyntax.login-1.1-py3.11-nspkg.pth
codesyntax/login/__init__.py
codesyntax/login/configure.zcml
codesyntax/login/interfaces.py
codesyntax/login/setuphandlers.py
codesyntax/login/testing.py
codesyntax/login/view.py
codesyntax/login/profiles/default/browserlayer.xml
codesyntax/login/profiles/default/catalog.xml
codesyntax/login/profiles/default/metadata.xml
codesyntax/login/profiles/default/rolemap.xml
codesyntax/login/profiles/default/registry/main.xml
codesyntax/login/profiles/uninstall/browserlayer.xml
codesyntax/login/tests/__init__.py
codesyntax/login/tests/test_robot.py
codesyntax/login/tests/test_setup.py
codesyntax/login/tests/robot/test_example.robot
codesyntax.login-1.1.dist-info/LICENSE.GPL
codesyntax.login-1.1.dist-info/LICENSE.rst
codesyntax.login-1.1.dist-info/METADATA
codesyntax.login-1.1.dist-info/WHEEL
codesyntax.login-1.1.dist-info/entry_points.txt
codesyntax.login-1.1.dist-info/namespace_packages.txt
codesyntax.login-1.1.dist-info/top_level.txt
codesyntax.login-1.1.dist-info/RECORD
